bamlib/__init__.py
bamlib/bamfuncs.py
bamlib-0.0.1.dist-info/LICENSE
bamlib-0.0.1.dist-info/METADATA
bamlib-0.0.1.dist-info/WHEEL
bamlib-0.0.1.dist-info/top_level.txt
bamlib-0.0.1.dist-info/RECORD
