Metadata-Version: 2.1
Name: bamlib
Version: 0.0.1
Summary: A python library that makes it easy to utilize the bank-account-microservice microservice.
Home-page: https://github.com/blarmon/bamlib
Author: Chris Siegel (https://github.com/blarmon)
Author-email: c.siegel1991@gmail.com
License: UNKNOWN
Platform: UNKNOWN
Classifier: Programming Language :: Python :: 3
Classifier: License :: OSI Approved :: MIT License
Classifier: Operating System :: OS Independent
